
{
  "Comment1": "Para validar el archivo ve a: http://www.jsoneditoronline.org/.",
  "Comment2": "Para adicionar una etiqueta, copie la primera y repitala al inicio. No copie la ultima y la copie al final.",
  "labels": [
    { 
      "name":       "Panel Fotovoltaico",
      "model":      "SAYA-M110-28",
      "template":   "SAYA-M110-28.png",
      
      "barcode_top":  1226,
      "barcode_left": 458,
      "date_top":     1269,
      "date_left":    93
    },
{ 
      "name":       "Panel Fotovoltaico",
      "model":      "SAYA-P50-36",
      "template":   "SAYA-P50-36.png",
      
      "barcode_top":  1226,
      "barcode_left": 458,
      "date_top":     1269,
      "date_left":    93
    },


    { 
      "name":       "Panel Fotovoltaico",
      "model":      "SAYA-M140-36",
      "template":   "SAYA-M140-36.png",
      
      "barcode_top":  1226,
      "barcode_left": 458,
      "date_top":     1269,
      "date_left":    93
    },
{ 
      "name":       "Panel Fotovoltaico",
      "model":      "SAYA-M145-36",
      "template":   "SAYA-M145-36.png",
      
      "barcode_top":  1226,
      "barcode_left": 458,
      "date_top":     1269,
      "date_left":    93
    },
{ 
      "name":       "Panel Fotovoltaico",
      "model":      "SAYA-P250-60",
      "template":   "SAYA-P250-60.png",
      
      "barcode_top":  1226,
      "barcode_left": 458,
      "date_top":     1269,
      "date_left":    93
    },
{ 
      "name":       "Panel Fotovoltaico",
      "model":      "SAYA-P270-60",
      "template":   "SAYA-P270-60.png",
      
      "barcode_top":  1226,
      "barcode_left": 458,
      "date_top":     1269,
      "date_left":    93
    },
{ 
      "name":       "Panel Fotovoltaico",
      "model":      "SAYA-P275-60",
      "template":   "SAYA-P275-60.png",
      
      "barcode_top":  1226,
      "barcode_left": 458,
      "date_top":     1269,
      "date_left":    93
    },

    { 
      "name":       "Panel Fotovoltaico",
      "model":      "SAYA-M250-60",
      "template":   "SAYA-M250-60.png",
      
      "barcode_top":  1226,
      "barcode_left": 458,
      "date_top":     1269,
      "date_left":    93
    },

 {
      "name":       "Panel Fotovoltaico",
      "model":      "SAYA-P100-28",
      "template":   "SAYA-P100-28.png",
      
      "barcode_top":  1226,
      "barcode_left": 458,
      "date_top":     1269,
      "date_left":    93
    },
 {
      "name":       "Panel Fotovoltaico",
      "model":      "SAYA-P120-28",
      "template":   "SAYA-P120-28.png",
      
      "barcode_top":  1226,
      "barcode_left": 458,
      "date_top":     1269,
      "date_left":    93
    },
{
      "name":       "Panel Fotovoltaico",
      "model":      "SAYA-P130-28",
      "template":   "SAYA-P130-28.png",
      
      "barcode_top":  1226,
      "barcode_left": 458,
      "date_top":     1269,
      "date_left":    93
    },
{
      "name":       "Panel Fotovoltaico",
      "model":      "SAYA-E120-28",
      "template":   "SAYA-E120-28.png",
      
      "barcode_top":  1226,
      "barcode_left": 458,
      "date_top":     1269,
      "date_left":    93
    },
{ 
      "name":       "Panel Fotovoltaico",
      "model":      "SAYA-P120-36",
      "template":   "SAYA-P120-36.png",
      
      "barcode_top":  1226,
      "barcode_left": 458,
      "date_top":     1269,
      "date_left":    93
    },

{ 
      "name":       "Panel Fotovoltaico",
      "model":      "SAYA-P150-36",
      "template":   "SAYA-P150-36.png",
      
      "barcode_top":  1226,
      "barcode_left": 458,
      "date_top":     1269,
      "date_left":    93
    },

{ 
      "name":       "Panel Fotovoltaico",
      "model":      "SAYA-M150-28",
      "template":   "SAYA-M150-28.png",
      
      "barcode_top":  1226,
      "barcode_left": 458,
      "date_top":     1269,
      "date_left":    93
    },

{ 
      "name":       "Panel Fotovoltaico",
      "model":      "SAYA-P170-36",
      "template":   "SAYA-P170-36.png",
      
      "barcode_top":  1226,
      "barcode_left": 458,
      "date_top":     1269,
      "date_left":    93
    },

{ 
      "name":       "Panel Fotovoltaico",
      "model":      "SAYA-M195-36",
      "template":   "SAYA-M195-36.png",
      
      "barcode_top":  1226,
      "barcode_left": 458,
      "date_top":     1269,
      "date_left":    93
    },
{
 
      "name":       "Panel Fotovoltaico",
      "model":      "SAYA-P190-54",
      "template":   "SAYA-P190-54.png",
      
      "barcode_top":  1226,
      "barcode_left": 458,
      "date_top":     1269,
      "date_left":    93
    },
{
 
      "name":       "Panel Fotovoltaico",
      "model":      "SAYA-P200-54",
      "template":   "SAYA-P200-54.png",
     
      "barcode_top":  1226,
      "barcode_left": 458,
      "date_top":     1269,
      "date_left":    93
    },

{
 
      "name":       "Panel Fotovoltaico",
      "model":      "SAYA-P220-60",
      "template":   "SAYA-P220-60.png",
      
      "barcode_top":  1226,
      "barcode_left": 458,
      "date_top":     1269,
      "date_left":    93
    },

{
 
      "name":       "Panel Fotovoltaico",
      "model":      "SAYA-P230-60",
      "template":   "SAYA-P230-60.png",
      
      "barcode_top":  1226,
      "barcode_left": 458,
      "date_top":     1269,
      "date_left":    93
    },
{
 
      "name":       "Panel Fotovoltaico",
      "model":      "SAYA-P250-54",
      "template":   "SAYA-P250-54.png",
      
      "barcode_top":  1226,
      "barcode_left": 458,
      "date_top":     1269,
      "date_left":    93
    },

{
 
      "name":       "Panel Fotovoltaico",
      "model":      "SAYA-P250-108",
      "template":   "SAYA-P250-108.png",
      
      "barcode_top":  1226,
      "barcode_left": 458,
      "date_top":     1269,
      "date_left":    93
    },
{
 
      "name":       "Panel Fotovoltaico",
      "model":      "SAYA-P240-60",
      "template":   "SAYA-P240-60.png",
      
      "barcode_top":  1226,
      "barcode_left": 458,
      "date_top":     1269,
      "date_left":    93
    },

{
 
      "name":       "Panel Fotovoltaico",
      "model":      "SAYA-P240-72",
      "template":   "SAYA-P240-72.png",
      
      "barcode_top":  1226,
      "barcode_left": 458,
      "date_top":     1269,
      "date_left":    93
    },
{
 
      "name":       "Panel Fotovoltaico",
      "model":      "SAYA-P250-72",
      "template":   "SAYA-P250-72.png",
      
      "barcode_top":  1226,
      "barcode_left": 458,
      "date_top":     1269,
      "date_left":    93
    },

    { 
      "name":       "Panel Fotovoltaico",
      "model":      "SAYA-M390-72",
      "template":   "SAYA-M390-72.png",
      
      "barcode_top":  1226,
      "barcode_left": 458,
      "date_top":     1269,
      "date_left":    93
    },

 { 
      "name":       "Panel Fotovoltaico",
      "model":      "SAYA-P300-72",
      "template":   "SAYA-P300-72.png",
      
      "barcode_top":  1226,
      "barcode_left": 458,
      "date_top":     1269,
      "date_left":    93
    },

   { 
      "name":       "Panel Fotovoltaico",
      "model":      "SAYA-P320-72",
      "template":   "SAYA-P320-72.png",
      
      "barcode_top":  1226,
      "barcode_left": 458,
      "date_top":     1269,
      "date_left":    93
    },
{ 
      "name":       "Panel Fotovoltaico",
      "model":      "SAYA-P330-72",
      "template":   "SAYA-P330-72.png",
      
      "barcode_top":  1226,
      "barcode_left": 458,
      "date_top":     1269,
      "date_left":    93
    },
    { 
      "name":       "Panel Fotovoltaico",
      "model":      "SAYA-P190-54",
      "template":   "SAYA-P190-54.png",
      
      "barcode_top":  1226,
      "barcode_left": 458,
      "date_top":     1269,
      "date_left":    93
    },
    { 
      "name":       "Panel Fotovoltaico",
      "model":      "SAYA-M110-28",
      
      "barcode_top":  1226,
      "barcode_left": 458,
      "date_top":     1269,
      "date_left":    93
    },
    { 
      "name":       "Panel Fotovoltaico",
      "model":      "SAYA-P270-72",
      "template":   "SAYA-P270-72.png",
      
      "barcode_top":  1226,
      "barcode_left": 458,
      "date_top":     1269,
      "date_left":    93
    },
    {
      "name":       "Panel Fotovoltaico",
      "model":      "SAYA-P290-72",
      "template":   "SAYA-P290-72.png",
      
      "barcode_top":  1226,
      "barcode_left": 458,
      "date_top":     1269,
      "date_left":    93

    },
{
      "name":       "Panel Fotovoltaico",
      "model":      "SAYA-P70-25",
      "template":   "SAYA-P70-25.png",
      
      "barcode_top":  1226,
      "barcode_left": 458,
      "date_top":     1269,
      "date_left":    93

    }
]
}
  
